{
  "interactionModel": {
    "languageModel": {
      "invocationName": "baby log",
      "intents": [
        {
          "name": "LogBottleFeedIntent",
          "slots": [
            { "name": "volume_value", "type": "AMAZON.NUMBER" },
            { "name": "volume_unit", "type": "VOLUME_UNIT" },
            { "name": "notes", "type": "AMAZON.SearchQuery" }
          ],
          "samples": [
            "log a bottle feed",
            "log a {volume_value} {volume_unit} bottle",
            "bottle {volume_value} {volume_unit}",
            "bottle {volume_value}",
            "bottle with {notes}",
            "log a bottle with {notes}",
            "record a bottle {volume_value} {volume_unit}"
          ]
        },
        {
          "name": "LogBreastFeedIntent",
          "slots": [
            { "name": "side", "type": "SIDE" },
            { "name": "duration_value", "type": "AMAZON.NUMBER" },
            { "name": "duration_unit", "type": "DURATION_UNIT" },
            { "name": "notes", "type": "AMAZON.SearchQuery" }
          ],
          "samples": [
            "log a breast feed",
            "breast {side}",
            "breast {side} for {duration_value} {duration_unit}",
            "breast for {duration_value} {duration_unit}",
            "breast with {notes}",
            "record a breast feed {side} for {duration_value} {duration_unit}"
          ]
        },
        {
          "name": "LogNappyIntent",
          "slots": [
            { "name": "type", "type": "NAPPY_TYPE" },
            { "name": "notes", "type": "AMAZON.SearchQuery" }
          ],
          "samples": [
            "log a {type} nappy",
            "{type} nappy",
            "log a nappy",
            "nappy with {notes}",
            "record a {type} nappy"
          ]
        },
        {
          "name": "LastFeedIntent",
          "samples": [
            "what was the last feed",
            "when was the last feed",
            "last bottle",
            "last feed",
            "when did baby last feed"
          ]
        },
        {
          "name": "StatsIntent",
          "slots": [
            { "name": "period", "type": "AMAZON.SearchQuery" }
          ],
          "samples": [
            "feeding stats for {period}",
            "how many feeds {period}",
            "stats {period}",
            "feeds {period}",
            "how many feeds today"
          ]
        },
        { "name": "AMAZON.YesIntent", "samples": [] },
        { "name": "AMAZON.NoIntent", "samples": [] },
        { "name": "AMAZON.HelpIntent", "samples": [] },
        { "name": "AMAZON.CancelIntent", "samples": [] },
        { "name": "AMAZON.StopIntent", "samples": [] },
        { "name": "AMAZON.FallbackIntent", "samples": [] }
      ],
      "types": [
        {
          "name": "SIDE",
          "values": [
            { "name": { "value": "left" } },
            { "name": { "value": "right" } }
          ]
        },
        {
          "name": "NAPPY_TYPE",
          "values": [
            {
              "name": { "value": "pee" },
              "id": "pee",
              "synonyms": ["number one", "number 1", "wee", "urine"]
            },
            {
              "name": { "value": "poo" },
              "id": "poo",
              "synonyms": ["number two", "number 2", "poop", "pooh", "stool", "faeces"]
            }
          ]
        },
        {
          "name": "VOLUME_UNIT",
          "values": [
            {
              "name": { "value": "millilitres" },
              "id": "ml",
              "synonyms": ["millilitre", "ml", "mil", "mills"]
            },
            {
              "name": { "value": "ounces" },
              "id": "oz",
              "synonyms": ["ounce", "oz", "fluid ounces", "fl oz"]
            }
          ]
        },
        {
          "name": "DURATION_UNIT",
          "values": [
            {
              "name": { "value": "minutes" },
              "id": "min",
              "synonyms": ["minute", "min", "mins"]
            },
            {
              "name": { "value": "hours" },
              "id": "h",
              "synonyms": ["hour", "hr", "hrs"]
            }
          ]
        }
      ]
    },
    "dialog": {
      "delegationStrategy": "SKILL_RESPONSE",
      "intents": [
        {
          "name": "LogBottleFeedIntent",
          "confirmationRequired": true,
          "prompts": { "confirmation": "Confirm.LogBottle" },
          "slots": [
            { "name": "volume_value", "type": "AMAZON.NUMBER", "elicitationRequired": false },
            { "name": "volume_unit", "type": "VOLUME_UNIT", "elicitationRequired": false },
            {
              "name": "notes",
              "type": "AMAZON.SearchQuery",
              "elicitationRequired": false,
              "prompts": { "elicitation": "Elicit.Notes" }
            }
          ]
        },
        {
          "name": "LogBreastFeedIntent",
          "confirmationRequired": true,
          "prompts": { "confirmation": "Confirm.LogBreast" },
          "slots": [
            {
              "name": "side",
              "type": "SIDE",
              "elicitationRequired": true,
              "prompts": { "elicitation": "Elicit.Side" }
            },
            { "name": "duration_value", "type": "AMAZON.NUMBER", "elicitationRequired": false },
            { "name": "duration_unit", "type": "DURATION_UNIT", "elicitationRequired": false },
            {
              "name": "notes",
              "type": "AMAZON.SearchQuery",
              "elicitationRequired": false,
              "prompts": { "elicitation": "Elicit.Notes" }
            }
          ]
        },
        {
          "name": "LogNappyIntent",
          "confirmationRequired": true,
          "prompts": { "confirmation": "Confirm.LogNappy" },
          "slots": [
            {
              "name": "type",
              "type": "NAPPY_TYPE",
              "elicitationRequired": true,
              "prompts": { "elicitation": "Elicit.NappyType" }
            },
            {
              "name": "notes",
              "type": "AMAZON.SearchQuery",
              "elicitationRequired": false,
              "prompts": { "elicitation": "Elicit.Notes" }
            }
          ]
        }
      ]
    },
    "prompts": [
      { "id": "Elicit.Side", "variations": [ { "type": "PlainText", "value": "Left or right side?" } ] },
      { "id": "Elicit.NappyType", "variations": [ { "type": "PlainText", "value": "Was it pee, or poo?" } ] },
      { "id": "Elicit.Notes", "variations": [ { "type": "PlainText", "value": "Any notes?" } ] },
      {
        "id": "Confirm.LogBottle",
        "variations": [ { "type": "PlainText", "value": "Log a bottle {volume_value} {volume_unit} {notes}. Is that right?" } ]
      },
      {
        "id": "Confirm.LogBreast",
        "variations": [
          { "type": "PlainText", "value": "Log a breast feed on the {side} {duration_value} {duration_unit} {notes}. Shall I save it?" }
        ]
      },
      {
        "id": "Confirm.LogNappy",
        "variations": [ { "type": "PlainText", "value": "Log a {type} nappy {notes}. Is that correct?" } ]
      }
    ]
  }
}
